{
  "name": "Doggystyle, Hair Pull",
  "modPack": "OpS",
  "length": 2,
  "navigations": [
    {
      "destination": "OpS_Kne!AFo_Sx_Doggystyle",
      "priority": 0,
      "noWarnings": false
    }
  ],
  "speeds": [
    {
      "animation": "_Sx-AceDoggystyleHairPull_S1",
      "playbackSpeed": 1,
      "displaySpeed": 0.5
    },
    {
      "animation": "_Sx-AceDoggystyleHairPull_S2",
      "playbackSpeed": 1,
      "displaySpeed": 1
    },
    {
      "animation": "_Sx-AceDoggystyleHairPull_S3",
      "playbackSpeed": 1,
      "displaySpeed": 1.5
    },
    {
      "animation": "_Sx-AceDoggystyleHairPull_S4",
      "playbackSpeed": 1,
      "displaySpeed": 2
    }
  ],
  "defaultSpeed": 0,
  "noRandomSelection": false,
  "tags": [
    "doggystyle"
  ],
  "autoTransitions": {},
  "actors": [
    {
      "type": "npc",
      "intendedSex": "any",
      "sosBend": 2,
      "scaleHeight": 120.748,
      "lookUp": -50,
      "tags": [
        "kneeling"
      ],
      "feetOnGround": false,
      "autoTransitions": {}
    },
    {
      "type": "npc",
      "intendedSex": "any",
      "scaleHeight": 120.748,
      "lookUp": -50,
      "tags": [
        "allfours",
        "facingaway"
      ],
      "feetOnGround": false,
      "autoTransitions": {}
    }
  ],
  "actions": [
    {
      "type": "vaginalsex",
      "actor": 0,
      "target": 1
    },
    {
      "type": "pullinghair",
      "actor": 1,
      "target": 1
    }
  ]
}