{
  "name": "Transition back from Vampire Bite Female Standing",
  "modPack": "OpS",
  "length": 2,
  "destination": "OARE_DevourDrainedMaleStanding",
  "navigations": [],
  "speeds": [],
  "defaultSpeed": 0,
  "noRandomSelection": false,
  "tags": [
    "transition"
  ],
  "autoTransitions": {},
  "actors": [
    {
      "type": "npc",
      "intendedSex": "any",
      "sosBend": -5,
      "scaleHeight": 120.748,
      "tags": [
        "drowsy",
        "standing"
      ],
      "feetOnGround": true,
      "autoTransitions": {}
    },
    {
      "type": "npc",
      "intendedSex": "any",
      "scaleHeight": 120.748,
      "tags": [
        "standing"
      ],
      "feetOnGround": true,
      "autoTransitions": {}
    }
  ],
  "actions": []
}